odoo8_addon_base_location_lau-8.0.1.0.0.99.dev7-nspkg.pth
odoo_addons/base_location_lau/README.rst
odoo_addons/base_location_lau/__init__.py
odoo_addons/base_location_lau/__openerp__.py
odoo_addons/base_location_lau/i18n/base_location_lau.pot
odoo_addons/base_location_lau/i18n/de.po
odoo_addons/base_location_lau/i18n/es.po
odoo_addons/base_location_lau/i18n/eu.po
odoo_addons/base_location_lau/i18n/sl.po
odoo_addons/base_location_lau/models/__init__.py
odoo_addons/base_location_lau/models/res_partner.py
odoo_addons/base_location_lau/models/res_partner_lau.py
odoo_addons/base_location_lau/security/ir.model.access.csv
odoo_addons/base_location_lau/static/description/icon.png
odoo_addons/base_location_lau/views/res_partner_lau_view.xml
odoo8_addon_base_location_lau-8.0.1.0.0.99.dev7.dist-info/METADATA
odoo8_addon_base_location_lau-8.0.1.0.0.99.dev7.dist-info/WHEEL
odoo8_addon_base_location_lau-8.0.1.0.0.99.dev7.dist-info/namespace_packages.txt
odoo8_addon_base_location_lau-8.0.1.0.0.99.dev7.dist-info/top_level.txt
odoo8_addon_base_location_lau-8.0.1.0.0.99.dev7.dist-info/RECORD
